{
  "2025-02-23": {
    "Temp_Actual": "6.0",
    "Temp_Trend": [
      -0.12,
      -0.11,
      -0.14,
      -0.14,
      -0.16,
      -0.14,
      -0.15,
      -0.12,
      -0.1,
      -0.12,
      -0.12,
      -0.15,
      -0.16,
      -0.17,
      -0.19,
      -0.18,
      -0.2,
      -0.2,
      -0.16,
      -0.12,
      -0.08,
      -0.18,
      -0.19,
      -0.19,
      -0.19,
      -0.21,
      -0.23,
      -0.18,
      -0.17,
      -0.19,
      -0.22,
      -0.19,
      -0.14,
      -0.07,
      -0.02,
      0.04,
      0.04,
      0.1,
      0.19,
      0.2,
      0.28,
      0.43,
      0.5,
      0.55,
      0.3,
      null,
      null,
      null,
      null,
      null,
      null,
      null,
      null,
      null,
      null,
      null,
      null,
      null,
      null,
      null,
      null,
      null,
      null,
      null,
      null,
      null,
      null,
      null,
      null,
      null,
      null,
      null,
      null,
      null,
      null,
      null,
      null,
      null,
      null,
      null,
      null,
      null,
      null,
      null,
      null,
      null,
      null,
      null,
      null,
      null,
      null,
      null,
      null,
      null,
      null,
      null,
      null,
      null,
      -0.12
    ],
    "Wind_Actual": "1.9",
    "Wind_Trend": [
      0.64,
      0.6,
      0.66,
      0.71,
      0.73,
      0.72,
      0.75,
      0.76,
      0.86,
      0.97,
      0.99,
      1.05,
      1.07,
      1.1,
      1.09,
      1.11,
      1.12,
      1.11,
      1.09,
      1.07,
      1.05,
      1.06,
      1.14,
      1.19,
      1.21,
      1.19,
      1.17,
      1.15,
      1.19,
      1.09,
      0.97,
      0.81,
      0.68,
      0.56,
      0.44,
      0.34,
      0.33,
      0.31,
      0.27,
      0.28,
      0.32,
      -0.03,
      0.03,
      -0.25,
      0.0,
      null,
      null,
      null,
      null,
      null,
      null,
      null,
      null,
      null,
      null,
      null,
      null,
      null,
      null,
      null,
      null,
      null,
      null,
      null,
      null,
      null,
      null,
      null,
      null,
      null,
      null,
      null,
      null,
      null,
      null,
      null,
      null,
      null,
      null,
      null,
      null,
      null,
      null,
      null,
      null,
      null,
      null,
      null,
      null,
      null,
      null,
      null,
      null,
      null,
      null,
      null,
      null,
      null,
      0.67
    ]
  },
  "2025-02-22": {
    "Temp_Actual": "5.0",
    "Temp_Trend": [
      0.1,
      0.19,
      0.24,
      0.31,
      0.32,
      0.32,
      0.32,
      0.29,
      0.26,
      0.18,
      0.12,
      0.07,
      0.07,
      0.12,
      0.18,
      0.21,
      0.08,
      -0.04,
      -0.2,
      -0.32,
      -0.25,
      -0.63,
      -0.6,
      -0.3,
      null,
      null,
      null,
      null,
      null,
      null,
      null,
      null,
      null,
      null,
      null,
      null,
      null,
      null,
      null,
      null,
      null,
      null,
      null,
      null,
      null,
      null,
      null,
      null,
      null,
      null,
      null,
      null,
      null,
      null,
      null,
      null,
      null,
      null,
      null,
      null,
      null,
      null,
      null,
      null,
      null,
      null,
      null,
      null,
      null,
      null,
      null,
      null,
      null,
      null,
      null,
      null,
      null,
      null,
      null,
      null,
      null,
      null,
      null,
      null,
      null,
      null,
      null,
      null,
      null,
      null,
      null,
      null,
      null,
      null,
      null,
      null,
      null,
      null,
      0.07
    ],
    "Wind_Actual": "3.7",
    "Wind_Trend": [
      1.38,
      1.4,
      1.42,
      1.39,
      1.42,
      1.47,
      1.47,
      1.45,
      1.51,
      1.55,
      1.57,
      1.58,
      1.58,
      1.62,
      1.7,
      1.76,
      1.8,
      1.83,
      1.75,
      1.64,
      1.58,
      1.6,
      1.95,
      1.9,
      null,
      null,
      null,
      null,
      null,
      null,
      null,
      null,
      null,
      null,
      null,
      null,
      null,
      null,
      null,
      null,
      null,
      null,
      null,
      null,
      null,
      null,
      null,
      null,
      null,
      null,
      null,
      null,
      null,
      null,
      null,
      null,
      null,
      null,
      null,
      null,
      null,
      null,
      null,
      null,
      null,
      null,
      null,
      null,
      null,
      null,
      null,
      null,
      null,
      null,
      null,
      null,
      null,
      null,
      null,
      null,
      null,
      null,
      null,
      null,
      null,
      null,
      null,
      null,
      null,
      null,
      null,
      null,
      null,
      null,
      null,
      null,
      null,
      null,
      1.35
    ]
  }
}